README.rst
setup.py
snormpy.py
snormpy.egg-info/PKG-INFO
snormpy.egg-info/SOURCES.txt
snormpy.egg-info/dependency_links.txt
snormpy.egg-info/top_level.txt